{
  "date": "2026-06-13",
  "generatedAt": "2026-06-13T09:40:52.266Z",
  "source": "/home/runner/work/dandom-market-stats/dandom-market-stats/strona-dan-dom/asari-export",
  "offerCount": 66,
  "offers": [
    {
      "signature": "128/6093/OGS",
      "title": "DZIAŁKA · GARBATKA",
      "category": "DZIAŁKA",
      "transaction": "SPRZEDAŻ",
      "status": "AKTUALNA",
      "city": "GARBATKA",
      "district": "",
      "locationLabel": "GARBATKA",
      "pricePln": 372120,
      "pricePerM2": 40,
      "areaM2": 9303,
      "rooms": null,
      "floor": null,
      "agentName": "Danuta Majchrzak",
      "listedAt": "2021-10-29",
      "lastModifiedAt": "2026-01-30",
      "firstSeenAt": "2026-03-24"
    },
    {
      "signature": "176/6093/ODS",
      "title": "Dom rekreacyjny Nienawiszcz niedaleko jezioro",
      "category": "DOM",
      "transaction": "SPRZEDAŻ",
      "status": "AKTUALNA",
      "city": "NIENAWISZCZ",
      "district": "Przepadek",
      "locationLabel": "Przepadek, NIENAWISZCZ",
      "pricePln": 269000,
      "pricePerM2": 4483,
      "areaM2": 60,
      "rooms": 3,
      "floor": null,
      "agentName": "Danuta Majchrzak",
      "listedAt": "2023-07-05",
      "lastModifiedAt": "2026-01-30",
      "firstSeenAt": "2026-03-24"
    },
    {
      "signature": "236/6093/ODS",
      "title": "Rezydencja nad jeziorem",
      "category": "DOM",
      "transaction": "SPRZEDAŻ",
      "status": "AKTUALNA",
      "city": "DŁUGA GOŚLINA",
      "district": "",
      "locationLabel": "DŁUGA GOŚLINA",
      "pricePln": 1999999,
      "pricePerM2": 3937,
      "areaM2": 508,
      "rooms": 7,
      "floor": null,
      "agentName": "Danuta Majchrzak",
      "listedAt": "2024-08-28",
      "lastModifiedAt": "2026-03-05",
      "firstSeenAt": "2026-03-24"
    },
    {
      "signature": "317/6093/OMS",
      "title": "Nowe mieszkania 3 pokoje, Kcynia ul. Młyńska",
      "category": "MIESZKANIE",
      "transaction": "SPRZEDAŻ",
      "status": "AKTUALNA",
      "city": "KCYNIA",
      "district": "Młyńska",
      "locationLabel": "Młyńska, KCYNIA",
      "pricePln": 323675,
      "pricePerM2": 5500,
      "areaM2": 58.85,
      "rooms": 3,
      "floor": 1,
      "agentName": "Danuta Majchrzak",
      "listedAt": "2024-09-26",
      "lastModifiedAt": "2026-06-11",
      "firstSeenAt": "2026-03-24"
    },
    {
      "signature": "193/6093/OGS",
      "title": "Działka budowlana w Runowie, gmina Wągrowiec",
      "category": "DZIAŁKA",
      "transaction": "SPRZEDAŻ",
      "status": "AKTUALNA",
      "city": "RUNOWO",
      "district": "",
      "locationLabel": "RUNOWO",
      "pricePln": 72000,
      "pricePerM2": 90,
      "areaM2": 800,
      "rooms": null,
      "floor": null,
      "agentName": "Danuta Majchrzak",
      "listedAt": "2024-11-05",
      "lastModifiedAt": "2026-01-30",
      "firstSeenAt": "2026-03-24"
    },
    {
      "signature": "199/6093/OGS",
      "title": "Działka budowlana w Grylewie",
      "category": "DZIAŁKA",
      "transaction": "SPRZEDAŻ",
      "status": "AKTUALNA",
      "city": "GRYLEWO",
      "district": "",
      "locationLabel": "GRYLEWO",
      "pricePln": 74640,
      "pricePerM2": 60,
      "areaM2": 1244,
      "rooms": null,
      "floor": null,
      "agentName": "Danuta Majchrzak",
      "listedAt": "2025-01-27",
      "lastModifiedAt": "2026-01-30",
      "firstSeenAt": "2026-03-24"
    },
    {
      "signature": "205/6093/OGS",
      "title": "Działka pod zabudowę mieszkaniową dwulokalową",
      "category": "DZIAŁKA",
      "transaction": "SPRZEDAŻ",
      "status": "AKTUALNA",
      "city": "ŁAZISKA",
      "district": "",
      "locationLabel": "ŁAZISKA",
      "pricePln": 328440,
      "pricePerM2": 105,
      "areaM2": 3128,
      "rooms": null,
      "floor": null,
      "agentName": "Danuta Majchrzak",
      "listedAt": "2025-03-17",
      "lastModifiedAt": "2026-01-30",
      "firstSeenAt": "2026-03-24"
    },
    {
      "signature": "208/6093/OGS",
      "title": "Ostatnia działka przy ul. Boguniewskiej.",
      "category": "DZIAŁKA",
      "transaction": "SPRZEDAŻ",
      "status": "AKTUALNA",
      "city": "ROGOŹNO",
      "district": "Boguniewska",
      "locationLabel": "Boguniewska, ROGOŹNO",
      "pricePln": 142920,
      "pricePerM2": 120,
      "areaM2": 1191,
      "rooms": null,
      "floor": null,
      "agentName": "Danuta Majchrzak",
      "listedAt": "2025-03-28",
      "lastModifiedAt": "2026-01-30",
      "firstSeenAt": "2026-03-24"
    },
    {
      "signature": "213/6093/OGS",
      "title": "Na sprzedaż działki przy lesie - Tarnowo, Rogoźno",
      "category": "DZIAŁKA",
      "transaction": "SPRZEDAŻ",
      "status": "AKTUALNA",
      "city": "TARNOWO",
      "district": "",
      "locationLabel": "TARNOWO",
      "pricePln": 95000,
      "pricePerM2": 30,
      "areaM2": 3198,
      "rooms": null,
      "floor": null,
      "agentName": "Danuta Majchrzak",
      "listedAt": "2025-04-22",
      "lastModifiedAt": "2026-01-30",
      "firstSeenAt": "2026-03-24"
    },
    {
      "signature": "216/6093/OGS",
      "title": "Działka nad jeziorem z pięknym widokiem na wodę",
      "category": "DZIAŁKA",
      "transaction": "SPRZEDAŻ",
      "status": "AKTUALNA",
      "city": "KALISKA",
      "district": "",
      "locationLabel": "KALISKA",
      "pricePln": 880000,
      "pricePerM2": 589,
      "areaM2": 1495,
      "rooms": null,
      "floor": null,
      "agentName": "Danuta Majchrzak",
      "listedAt": "2025-05-21",
      "lastModifiedAt": "2026-01-30",
      "firstSeenAt": "2026-03-24"
    },
    {
      "signature": "217/6093/OGS",
      "title": "Działka w Zbietce gmina Mieścisko",
      "category": "DZIAŁKA",
      "transaction": "SPRZEDAŻ",
      "status": "AKTUALNA",
      "city": "ZBIETKA",
      "district": "",
      "locationLabel": "ZBIETKA",
      "pricePln": 79000,
      "pricePerM2": 65,
      "areaM2": 1220,
      "rooms": null,
      "floor": null,
      "agentName": "Danuta Majchrzak",
      "listedAt": "2025-05-21",
      "lastModifiedAt": "2026-01-30",
      "firstSeenAt": "2026-03-24"
    },
    {
      "signature": "218/6093/OGS",
      "title": "Atrakcyjna działka dookoła natura - las jezioro",
      "category": "DZIAŁKA",
      "transaction": "SPRZEDAŻ",
      "status": "AKTUALNA",
      "city": "BOGUNIEWO",
      "district": "",
      "locationLabel": "BOGUNIEWO",
      "pricePln": 189000,
      "pricePerM2": 95,
      "areaM2": 1998,
      "rooms": null,
      "floor": null,
      "agentName": "Danuta Majchrzak",
      "listedAt": "2025-05-27",
      "lastModifiedAt": "2026-01-30",
      "firstSeenAt": "2026-03-24"
    },
    {
      "signature": "272/6093/ODS",
      "title": "Dom jednorodzinny w Rogoźnie",
      "category": "DOM",
      "transaction": "SPRZEDAŻ",
      "status": "AKTUALNA",
      "city": "ROGOŹNO",
      "district": "Reja",
      "locationLabel": "Reja, ROGOŹNO",
      "pricePln": 480000,
      "pricePerM2": 2595,
      "areaM2": 185,
      "rooms": 5,
      "floor": null,
      "agentName": "Danuta Majchrzak",
      "listedAt": "2025-07-03",
      "lastModifiedAt": "2026-05-29",
      "firstSeenAt": "2026-03-24"
    },
    {
      "signature": "222/6093/OGS",
      "title": "Oaza spokoju - działka z drzewami w Łaziskach",
      "category": "DZIAŁKA",
      "transaction": "SPRZEDAŻ",
      "status": "AKTUALNA",
      "city": "ŁAZISKA",
      "district": "",
      "locationLabel": "ŁAZISKA",
      "pricePln": 728000,
      "pricePerM2": 140,
      "areaM2": 5200,
      "rooms": null,
      "floor": null,
      "agentName": "Danuta Majchrzak",
      "listedAt": "2025-07-17",
      "lastModifiedAt": "2026-01-30",
      "firstSeenAt": "2026-03-24"
    },
    {
      "signature": "364/6093/OMS",
      "title": "Mieszkanie 2 pokojowe Jeżyka Wągrowiec",
      "category": "MIESZKANIE",
      "transaction": "SPRZEDAŻ",
      "status": "AKTUALNA",
      "city": "WĄGROWIEC",
      "district": "Jeżyka",
      "locationLabel": "Jeżyka, WĄGROWIEC",
      "pricePln": 270000,
      "pricePerM2": 5625,
      "areaM2": 48,
      "rooms": 2,
      "floor": 4,
      "agentName": "Danuta Majchrzak",
      "listedAt": "2025-08-27",
      "lastModifiedAt": "2026-01-30",
      "firstSeenAt": "2026-03-24"
    },
    {
      "signature": "224/6093/OGS",
      "title": "Działka budowlana - piękne położenie Bolechówko",
      "category": "DZIAŁKA",
      "transaction": "SPRZEDAŻ",
      "status": "AKTUALNA",
      "city": "BOLECHÓWKO",
      "district": "Kręta",
      "locationLabel": "Kręta, BOLECHÓWKO",
      "pricePln": 416625,
      "pricePerM2": 275,
      "areaM2": 1515,
      "rooms": null,
      "floor": null,
      "agentName": "Danuta Majchrzak",
      "listedAt": "2025-08-27",
      "lastModifiedAt": "2026-01-30",
      "firstSeenAt": "2026-03-24"
    },
    {
      "signature": "225/6093/OGS",
      "title": "Działka z możliwością zabudowy jednorodzinnej",
      "category": "DZIAŁKA",
      "transaction": "SPRZEDAŻ",
      "status": "AKTUALNA",
      "city": "BRZEŹNO STARE",
      "district": "",
      "locationLabel": "BRZEŹNO STARE",
      "pricePln": 88920,
      "pricePerM2": 90,
      "areaM2": 988,
      "rooms": null,
      "floor": null,
      "agentName": "Danuta Majchrzak",
      "listedAt": "2025-09-26",
      "lastModifiedAt": "2026-01-30",
      "firstSeenAt": "2026-03-24"
    },
    {
      "signature": "372/6093/OMS",
      "title": "Bezczynszowe 2 pokoje z aneksem Wegnera Wągrowiec",
      "category": "MIESZKANIE",
      "transaction": "SPRZEDAŻ",
      "status": "AKTUALNA",
      "city": "WĄGROWIEC",
      "district": "Ignacego Wegnera",
      "locationLabel": "Ignacego Wegnera, WĄGROWIEC",
      "pricePln": 330000,
      "pricePerM2": 8070,
      "areaM2": 40.89,
      "rooms": 2,
      "floor": 3,
      "agentName": "Danuta Majchrzak",
      "listedAt": "2025-09-29",
      "lastModifiedAt": "2026-05-22",
      "firstSeenAt": "2026-03-24"
    },
    {
      "signature": "373/6093/OMS",
      "title": "Stylowe mieszkanie po remoncie",
      "category": "MIESZKANIE",
      "transaction": "SPRZEDAŻ",
      "status": "AKTUALNA",
      "city": "ROGOŹNO",
      "district": "Plac Powstańców Wielkopolskich",
      "locationLabel": "Plac Powstańców Wielkopolskich, ROGOŹNO",
      "pricePln": 359000,
      "pricePerM2": 2532,
      "areaM2": 141.79,
      "rooms": 5,
      "floor": 2,
      "agentName": "Danuta Majchrzak",
      "listedAt": "2025-10-01",
      "lastModifiedAt": "2026-05-14",
      "firstSeenAt": "2026-03-24"
    },
    {
      "signature": "226/6093/OGS",
      "title": "Piękna duża działka pod zabudowę Brzeźno Stare",
      "category": "DZIAŁKA",
      "transaction": "SPRZEDAŻ",
      "status": "AKTUALNA",
      "city": "BRZEŹNO STARE",
      "district": "",
      "locationLabel": "BRZEŹNO STARE",
      "pricePln": 200000,
      "pricePerM2": 32,
      "areaM2": 6338,
      "rooms": null,
      "floor": null,
      "agentName": "Danuta Majchrzak",
      "listedAt": "2025-10-03",
      "lastModifiedAt": "2026-04-10",
      "firstSeenAt": "2026-03-24"
    },
    {
      "signature": "378/6093/OMS",
      "title": "Poranna kawa na własnym tarasie, 3 pokoje czekają!",
      "category": "MIESZKANIE",
      "transaction": "SPRZEDAŻ",
      "status": "AKTUALNA",
      "city": "WĄGROWIEC",
      "district": "Stanisława Mikołajczyka",
      "locationLabel": "Stanisława Mikołajczyka, WĄGROWIEC",
      "pricePln": 439000,
      "pricePerM2": 8869,
      "areaM2": 49.5,
      "rooms": 3,
      "floor": 0,
      "agentName": "Danuta Majchrzak",
      "listedAt": "2025-10-21",
      "lastModifiedAt": "2026-04-08",
      "firstSeenAt": "2026-03-24"
    },
    {
      "signature": "227/6093/OGS",
      "title": "Działka na terenach inwestycyjnych m. Rogoźno",
      "category": "DZIAŁKA",
      "transaction": "SPRZEDAŻ",
      "status": "AKTUALNA",
      "city": "GARBATKA",
      "district": "",
      "locationLabel": "GARBATKA",
      "pricePln": 480160,
      "pricePerM2": 40,
      "areaM2": 12004,
      "rooms": null,
      "floor": null,
      "agentName": "Danuta Majchrzak",
      "listedAt": "2025-10-22",
      "lastModifiedAt": "2026-01-30",
      "firstSeenAt": "2026-03-24"
    },
    {
      "signature": "280/6093/ODS",
      "title": "Przestronny dom pod miastem - cisza i wygoda",
      "category": "DOM",
      "transaction": "SPRZEDAŻ",
      "status": "AKTUALNA",
      "city": "ŁAZISKA",
      "district": "",
      "locationLabel": "ŁAZISKA",
      "pricePln": 1149000,
      "pricePerM2": 4256,
      "areaM2": 270,
      "rooms": 6,
      "floor": null,
      "agentName": "Danuta Majchrzak",
      "listedAt": "2025-10-24",
      "lastModifiedAt": "2026-05-12",
      "firstSeenAt": "2026-03-24"
    },
    {
      "signature": "228/6093/OGS",
      "title": "Twoje miejsce na wypoczynek - jezioro i piękny las",
      "category": "DZIAŁKA",
      "transaction": "SPRZEDAŻ",
      "status": "AKTUALNA",
      "city": "OKONINY NADJEZIORNE",
      "district": "",
      "locationLabel": "OKONINY NADJEZIORNE",
      "pricePln": 116285,
      "pricePerM2": 65,
      "areaM2": 1789,
      "rooms": null,
      "floor": null,
      "agentName": "Danuta Majchrzak",
      "listedAt": "2025-11-27",
      "lastModifiedAt": "2026-05-25",
      "firstSeenAt": "2026-03-24"
    },
    {
      "signature": "287/6093/ODS",
      "title": "DOM · ROGOŹNO",
      "category": "DOM",
      "transaction": "SPRZEDAŻ",
      "status": "AKTUALNA",
      "city": "ROGOŹNO",
      "district": "Wielka Poznańska",
      "locationLabel": "Wielka Poznańska, ROGOŹNO",
      "pricePln": 260000,
      "pricePerM2": 2600,
      "areaM2": 100,
      "rooms": 5,
      "floor": null,
      "agentName": "Danuta Majchrzak",
      "listedAt": "2026-01-12",
      "lastModifiedAt": "2026-03-06",
      "firstSeenAt": "2026-03-24"
    },
    {
      "signature": "230/6093/OGS",
      "title": "Działka pod zabudowę Wągrowiec ul. Wierzbowa",
      "category": "DZIAŁKA",
      "transaction": "SPRZEDAŻ",
      "status": "AKTUALNA",
      "city": "WĄGROWIEC",
      "district": "Wierzbowa",
      "locationLabel": "Wierzbowa, WĄGROWIEC",
      "pricePln": 260000,
      "pricePerM2": 267,
      "areaM2": 975,
      "rooms": null,
      "floor": null,
      "agentName": "Danuta Majchrzak",
      "listedAt": "2026-01-14",
      "lastModifiedAt": "2026-06-12",
      "firstSeenAt": "2026-03-24"
    },
    {
      "signature": "290/6093/ODS",
      "title": "Nowoczesny dom jednorodzinny z garażem",
      "category": "DOM",
      "transaction": "SPRZEDAŻ",
      "status": "AKTUALNA",
      "city": "GARBATKA",
      "district": "",
      "locationLabel": "GARBATKA",
      "pricePln": 920000,
      "pricePerM2": 7931,
      "areaM2": 116,
      "rooms": 4,
      "floor": null,
      "agentName": "Danuta Majchrzak",
      "listedAt": "2026-01-20",
      "lastModifiedAt": "2026-05-20",
      "firstSeenAt": "2026-03-24"
    },
    {
      "signature": "231/6093/OGS",
      "title": "Duża działka budowlana",
      "category": "DZIAŁKA",
      "transaction": "SPRZEDAŻ",
      "status": "AKTUALNA",
      "city": "STUDZIENIEC",
      "district": "",
      "locationLabel": "STUDZIENIEC",
      "pricePln": 205000,
      "pricePerM2": 98,
      "areaM2": 2085,
      "rooms": null,
      "floor": null,
      "agentName": "Danuta Majchrzak",
      "listedAt": "2026-02-06",
      "lastModifiedAt": "2026-04-08",
      "firstSeenAt": "2026-03-24"
    },
    {
      "signature": "398/6093/OMS",
      "title": "Mieszkanie na parterze z balkonem",
      "category": "MIESZKANIE",
      "transaction": "SPRZEDAŻ",
      "status": "AKTUALNA",
      "city": "ROGOŹNO",
      "district": "Wojska Polskiego",
      "locationLabel": "Wojska Polskiego, ROGOŹNO",
      "pricePln": 199000,
      "pricePerM2": 3864,
      "areaM2": 51.5,
      "rooms": 2,
      "floor": 0,
      "agentName": "Danuta Majchrzak",
      "listedAt": "2026-02-10",
      "lastModifiedAt": "2026-04-22",
      "firstSeenAt": "2026-03-24"
    },
    {
      "signature": "403/6093/OMS",
      "title": "Mieszkanie w bloku na parterze",
      "category": "MIESZKANIE",
      "transaction": "SPRZEDAŻ",
      "status": "AKTUALNA",
      "city": "ROGOŹNO",
      "district": "Osiedle Przemysława II",
      "locationLabel": "Osiedle Przemysława II, ROGOŹNO",
      "pricePln": 209000,
      "pricePerM2": 5679,
      "areaM2": 36.8,
      "rooms": 2,
      "floor": 0,
      "agentName": "Danuta Majchrzak",
      "listedAt": "2026-02-26",
      "lastModifiedAt": "2026-03-24",
      "firstSeenAt": "2026-03-24"
    },
    {
      "signature": "298/6093/ODS",
      "title": "Dom w bliskiej okolicy jeziora Wągrowiec",
      "category": "DOM",
      "transaction": "SPRZEDAŻ",
      "status": "AKTUALNA",
      "city": "WĄGROWIEC",
      "district": "",
      "locationLabel": "WĄGROWIEC",
      "pricePln": 520000,
      "pricePerM2": 2374,
      "areaM2": 219,
      "rooms": 5,
      "floor": null,
      "agentName": "Danuta Majchrzak",
      "listedAt": "2026-03-03",
      "lastModifiedAt": "2026-04-13",
      "firstSeenAt": "2026-03-24"
    },
    {
      "signature": "406/6093/OMS",
      "title": "MIESZKANIE · ROGOŹNO",
      "category": "MIESZKANIE",
      "transaction": "SPRZEDAŻ",
      "status": "AKTUALNA",
      "city": "ROGOŹNO",
      "district": "Wielka Poznańska",
      "locationLabel": "Wielka Poznańska, ROGOŹNO",
      "pricePln": 189000,
      "pricePerM2": 5354,
      "areaM2": 35.3,
      "rooms": 2,
      "floor": 1,
      "agentName": "Danuta Majchrzak",
      "listedAt": "2026-03-10",
      "lastModifiedAt": "2026-03-10",
      "firstSeenAt": "2026-03-24"
    },
    {
      "signature": "9/6093/OOS",
      "title": "Zakład usługowo- produkcyjny",
      "category": "OBIEKT",
      "transaction": "SPRZEDAŻ",
      "status": "AKTUALNA",
      "city": "ROGOŹNO",
      "district": "",
      "locationLabel": "ROGOŹNO",
      "pricePln": 1120000,
      "pricePerM2": 4978,
      "areaM2": 225,
      "rooms": null,
      "floor": null,
      "agentName": "Danuta Majchrzak",
      "listedAt": "2026-03-11",
      "lastModifiedAt": "2026-04-22",
      "firstSeenAt": "2026-03-24"
    },
    {
      "signature": "232/6093/OGS",
      "title": "Piękna działka Wiatrowo Las z pozwoleniem",
      "category": "DZIAŁKA",
      "transaction": "SPRZEDAŻ",
      "status": "AKTUALNA",
      "city": "WIATROWO",
      "district": "",
      "locationLabel": "WIATROWO",
      "pricePln": 360000,
      "pricePerM2": 187,
      "areaM2": 1925,
      "rooms": null,
      "floor": null,
      "agentName": "Danuta Majchrzak",
      "listedAt": "2026-03-11",
      "lastModifiedAt": "2026-06-12",
      "firstSeenAt": "2026-03-24"
    },
    {
      "signature": "301/6093/ODS",
      "title": "DOM · KOBYLEC",
      "category": "DOM",
      "transaction": "SPRZEDAŻ",
      "status": "AKTUALNA",
      "city": "KOBYLEC",
      "district": "",
      "locationLabel": "KOBYLEC",
      "pricePln": 925000,
      "pricePerM2": 5892,
      "areaM2": 157,
      "rooms": 4,
      "floor": null,
      "agentName": "Danuta Majchrzak",
      "listedAt": "2026-03-30",
      "lastModifiedAt": "2026-06-01",
      "firstSeenAt": "2026-04-01"
    },
    {
      "signature": "410/6093/OMS",
      "title": "2 pokoje na II piętrze w bezczynszowym bloku",
      "category": "MIESZKANIE",
      "transaction": "SPRZEDAŻ",
      "status": "AKTUALNA",
      "city": "WĄGROWIEC",
      "district": "Straszewska",
      "locationLabel": "Straszewska, WĄGROWIEC",
      "pricePln": 309000,
      "pricePerM2": 6131,
      "areaM2": 50.4,
      "rooms": 2,
      "floor": 2,
      "agentName": "Danuta Majchrzak",
      "listedAt": "2026-04-02",
      "lastModifiedAt": "2026-05-19",
      "firstSeenAt": "2026-04-07"
    },
    {
      "signature": "237/6093/OGS",
      "title": "Działka budowlana- Nienawiszcz",
      "category": "DZIAŁKA",
      "transaction": "SPRZEDAŻ",
      "status": "AKTUALNA",
      "city": "NIENAWISZCZ",
      "district": "",
      "locationLabel": "NIENAWISZCZ",
      "pricePln": 105500,
      "pricePerM2": 100,
      "areaM2": 1055,
      "rooms": null,
      "floor": null,
      "agentName": "Danuta Majchrzak",
      "listedAt": "2026-04-09",
      "lastModifiedAt": "2026-06-08",
      "firstSeenAt": "2026-04-20"
    },
    {
      "signature": "302/6093/ODS",
      "title": "Cisza, przestrzeń i szybki dojazd dom k. Wągrowca",
      "category": "DOM",
      "transaction": "SPRZEDAŻ",
      "status": "AKTUALNA",
      "city": "OCHODZA",
      "district": "",
      "locationLabel": "OCHODZA",
      "pricePln": 950000,
      "pricePerM2": 5404,
      "areaM2": 175.78,
      "rooms": 4,
      "floor": null,
      "agentName": "Danuta Majchrzak",
      "listedAt": "2026-04-21",
      "lastModifiedAt": "2026-04-24",
      "firstSeenAt": "2026-04-21"
    },
    {
      "signature": "304/6093/ODS",
      "title": "Spokój, natura i nowoczesność - dom  pod Wągrowcem",
      "category": "DOM",
      "transaction": "SPRZEDAŻ",
      "status": "AKTUALNA",
      "city": "WIATROWIEC",
      "district": "",
      "locationLabel": "WIATROWIEC",
      "pricePln": 659900,
      "pricePerM2": 6747,
      "areaM2": 97.8,
      "rooms": 4,
      "floor": null,
      "agentName": "Danuta Majchrzak",
      "listedAt": "2026-04-24",
      "lastModifiedAt": "2026-04-27",
      "firstSeenAt": "2026-04-27"
    },
    {
      "signature": "418/6093/OMS",
      "title": "Rogoźno, ul. Strzelecka- ostatnie mieszkanie!!!",
      "category": "MIESZKANIE",
      "transaction": "SPRZEDAŻ",
      "status": "AKTUALNA",
      "city": "ROGOŹNO",
      "district": "Strzelecka",
      "locationLabel": "Strzelecka, ROGOŹNO",
      "pricePln": 320000,
      "pricePerM2": 6855,
      "areaM2": 46.68,
      "rooms": 3,
      "floor": 2,
      "agentName": "Danuta Majchrzak",
      "listedAt": "2026-04-28",
      "lastModifiedAt": "2026-06-10",
      "firstSeenAt": "2026-04-28"
    },
    {
      "signature": "291/6093/ODS",
      "title": "Piękna leśna działka z domem - Oaza Spokoju",
      "category": "DOM",
      "transaction": "SPRZEDAŻ",
      "status": "AKTUALNA",
      "city": "RUDNICZE",
      "district": "",
      "locationLabel": "RUDNICZE",
      "pricePln": 1390000,
      "pricePerM2": 12411,
      "areaM2": 112,
      "rooms": 4,
      "floor": null,
      "agentName": "Danuta Majchrzak",
      "listedAt": "2026-01-27",
      "lastModifiedAt": "2026-04-28",
      "firstSeenAt": "2026-03-24"
    },
    {
      "signature": "305/6093/ODS",
      "title": "DOM · WĄGROWIEC",
      "category": "DOM",
      "transaction": "SPRZEDAŻ",
      "status": "AKTUALNA",
      "city": "WĄGROWIEC",
      "district": "Leszczynowa",
      "locationLabel": "Leszczynowa, WĄGROWIEC",
      "pricePln": 699000,
      "pricePerM2": 4854,
      "areaM2": 144,
      "rooms": 5,
      "floor": null,
      "agentName": "Danuta Majchrzak",
      "listedAt": "2026-04-24",
      "lastModifiedAt": "2026-04-29",
      "firstSeenAt": "2026-04-29"
    },
    {
      "signature": "306/6093/ODS",
      "title": "Segment z działką Ruda k. Rogoźna",
      "category": "DOM",
      "transaction": "SPRZEDAŻ",
      "status": "AKTUALNA",
      "city": "ROGOŹNO",
      "district": "",
      "locationLabel": "ROGOŹNO",
      "pricePln": 399000,
      "pricePerM2": 5809,
      "areaM2": 68.69,
      "rooms": 4,
      "floor": null,
      "agentName": "Danuta Majchrzak",
      "listedAt": "2026-04-29",
      "lastModifiedAt": "2026-06-08",
      "firstSeenAt": "2026-04-29"
    },
    {
      "signature": "238/6093/OGS",
      "title": "Zbuduj swój dom w historycznym sercu Pałuk",
      "category": "DZIAŁKA",
      "transaction": "SPRZEDAŻ",
      "status": "AKTUALNA",
      "city": "PANIGRÓDZ",
      "district": "",
      "locationLabel": "PANIGRÓDZ",
      "pricePln": 219000,
      "pricePerM2": 54,
      "areaM2": 4056,
      "rooms": null,
      "floor": null,
      "agentName": "Danuta Majchrzak",
      "listedAt": "2026-05-04",
      "lastModifiedAt": "2026-05-05",
      "firstSeenAt": "2026-05-05"
    },
    {
      "signature": "239/6093/OGS",
      "title": "Działka z warunkami zabudowy Łekno",
      "category": "DZIAŁKA",
      "transaction": "SPRZEDAŻ",
      "status": "AKTUALNA",
      "city": "ŁEKNO",
      "district": "",
      "locationLabel": "ŁEKNO",
      "pricePln": 49000,
      "pricePerM2": 54,
      "areaM2": 905,
      "rooms": null,
      "floor": null,
      "agentName": "Danuta Majchrzak",
      "listedAt": "2026-05-07",
      "lastModifiedAt": "2026-05-07",
      "firstSeenAt": "2026-05-07"
    },
    {
      "signature": "417/6093/OMS",
      "title": "Mieszkanie 2 pokojowe w Karolewie, gm. Rogoźno",
      "category": "MIESZKANIE",
      "transaction": "SPRZEDAŻ",
      "status": "AKTUALNA",
      "city": "KAROLEWO",
      "district": "",
      "locationLabel": "KAROLEWO",
      "pricePln": 129000,
      "pricePerM2": 2596,
      "areaM2": 49.7,
      "rooms": 2,
      "floor": 1,
      "agentName": "Danuta Majchrzak",
      "listedAt": "2026-04-27",
      "lastModifiedAt": "2026-06-10",
      "firstSeenAt": "2026-05-08"
    },
    {
      "signature": "307/6093/ODS",
      "title": "Ucieknij na wieś: Stan surowy otulony zielenią",
      "category": "DOM",
      "transaction": "SPRZEDAŻ",
      "status": "AKTUALNA",
      "city": "STAWIANY",
      "district": "",
      "locationLabel": "STAWIANY",
      "pricePln": 365000,
      "pricePerM2": 2736,
      "areaM2": 133.4,
      "rooms": 4,
      "floor": null,
      "agentName": "Danuta Majchrzak",
      "listedAt": "2026-05-04",
      "lastModifiedAt": "2026-05-25",
      "firstSeenAt": "2026-05-11"
    },
    {
      "signature": "308/6093/ODS",
      "title": "Mały dom w Kobylcu –  blisko jeziora i lasu!",
      "category": "DOM",
      "transaction": "SPRZEDAŻ",
      "status": "AKTUALNA",
      "city": "KOBYLEC",
      "district": "Winogronowa",
      "locationLabel": "Winogronowa, KOBYLEC",
      "pricePln": 320000,
      "pricePerM2": 4540,
      "areaM2": 70.48,
      "rooms": 4,
      "floor": null,
      "agentName": "Danuta Majchrzak",
      "listedAt": "2026-05-06",
      "lastModifiedAt": "2026-05-14",
      "firstSeenAt": "2026-05-14"
    },
    {
      "signature": "419/6093/OMS",
      "title": "Mieszkanie 2-pokojowe na parterze z klimatyzacją",
      "category": "MIESZKANIE",
      "transaction": "SPRZEDAŻ",
      "status": "AKTUALNA",
      "city": "ROGOŹNO",
      "district": "Kościuszki",
      "locationLabel": "Kościuszki, ROGOŹNO",
      "pricePln": 259000,
      "pricePerM2": 6106,
      "areaM2": 42.42,
      "rooms": 2,
      "floor": 0,
      "agentName": "Danuta Majchrzak",
      "listedAt": "2026-05-13",
      "lastModifiedAt": "2026-06-02",
      "firstSeenAt": "2026-05-20"
    },
    {
      "signature": "309/6093/ODS",
      "title": "Połączenie idealne: Przestrzeń domu w centrum!",
      "category": "DOM",
      "transaction": "SPRZEDAŻ",
      "status": "AKTUALNA",
      "city": "ROGOŹNO",
      "district": "Nowa",
      "locationLabel": "Nowa, ROGOŹNO",
      "pricePln": 890000,
      "pricePerM2": 7037,
      "areaM2": 126.48,
      "rooms": 4,
      "floor": null,
      "agentName": "Danuta Majchrzak",
      "listedAt": "2026-05-15",
      "lastModifiedAt": "2026-05-27",
      "firstSeenAt": "2026-05-20"
    },
    {
      "signature": "303/6093/ODS",
      "title": "Rezydencja marzeń niedaleko jeziora – oaza ciszy",
      "category": "DOM",
      "transaction": "SPRZEDAŻ",
      "status": "AKTUALNA",
      "city": "WĄGROWIEC",
      "district": "",
      "locationLabel": "WĄGROWIEC",
      "pricePln": 2490000,
      "pricePerM2": 11636,
      "areaM2": 214,
      "rooms": 5,
      "floor": null,
      "agentName": "Danuta Majchrzak",
      "listedAt": "2026-04-23",
      "lastModifiedAt": "2026-05-20",
      "firstSeenAt": "2026-05-20"
    },
    {
      "signature": "420/6093/OMS",
      "title": "Przyjemna kawalerka - Lipowa, Wągrowiec",
      "category": "MIESZKANIE",
      "transaction": "SPRZEDAŻ",
      "status": "AKTUALNA",
      "city": "WĄGROWIEC",
      "district": "Lipowa",
      "locationLabel": "Lipowa, WĄGROWIEC",
      "pricePln": 205000,
      "pricePerM2": 6926,
      "areaM2": 29.6,
      "rooms": 1,
      "floor": 4,
      "agentName": "Danuta Majchrzak",
      "listedAt": "2026-05-21",
      "lastModifiedAt": "2026-06-11",
      "firstSeenAt": "2026-05-21"
    },
    {
      "signature": "310/6093/ODS",
      "title": "Przestronny dom wolnostojący – idealna cisza",
      "category": "DOM",
      "transaction": "SPRZEDAŻ",
      "status": "AKTUALNA",
      "city": "WĄGROWIEC",
      "district": "Bażantowa",
      "locationLabel": "Bażantowa, WĄGROWIEC",
      "pricePln": 830000,
      "pricePerM2": 5000,
      "areaM2": 166,
      "rooms": 5,
      "floor": null,
      "agentName": "Danuta Majchrzak",
      "listedAt": "2026-05-20",
      "lastModifiedAt": "2026-05-22",
      "firstSeenAt": "2026-05-22"
    },
    {
      "signature": "421/6093/OMS",
      "title": "Całkowicie wyposażone mieszkanie z windą Wegnera",
      "category": "MIESZKANIE",
      "transaction": "SPRZEDAŻ",
      "status": "AKTUALNA",
      "city": "WĄGROWIEC",
      "district": "Ignacego Wegnera",
      "locationLabel": "Ignacego Wegnera, WĄGROWIEC",
      "pricePln": 480000,
      "pricePerM2": 8738,
      "areaM2": 54.93,
      "rooms": 3,
      "floor": 2,
      "agentName": "Danuta Majchrzak",
      "listedAt": "2026-05-22",
      "lastModifiedAt": "2026-05-25",
      "firstSeenAt": "2026-05-25"
    },
    {
      "signature": "109/6093/OMW",
      "title": "Na wynajem lokal mieszkalny",
      "category": "MIESZKANIE",
      "transaction": "WYNAJEM",
      "status": "AKTUALNA",
      "city": "CIEŚLE",
      "district": "",
      "locationLabel": "CIEŚLE",
      "pricePln": 1300,
      "pricePerM2": 33,
      "areaM2": 40,
      "rooms": 1,
      "floor": 0,
      "agentName": "Danuta Majchrzak",
      "listedAt": "2026-05-25",
      "lastModifiedAt": "2026-05-26",
      "firstSeenAt": "2026-05-26"
    },
    {
      "signature": "311/6093/ODS",
      "title": "Zaprojektuj od zera: Dom z potencjałem Wągrowiec",
      "category": "DOM",
      "transaction": "SPRZEDAŻ",
      "status": "AKTUALNA",
      "city": "WĄGROWIEC",
      "district": "Pawła E. Strzeleckiego",
      "locationLabel": "Pawła E. Strzeleckiego, WĄGROWIEC",
      "pricePln": 459000,
      "pricePerM2": 3454,
      "areaM2": 130,
      "rooms": 6,
      "floor": null,
      "agentName": "Danuta Majchrzak",
      "listedAt": "2026-05-21",
      "lastModifiedAt": "2026-05-27",
      "firstSeenAt": "2026-05-26"
    },
    {
      "signature": "312/6093/ODS",
      "title": "Dom w spokojnej części Wągrowca",
      "category": "DOM",
      "transaction": "SPRZEDAŻ",
      "status": "AKTUALNA",
      "city": "WĄGROWIEC",
      "district": "",
      "locationLabel": "WĄGROWIEC",
      "pricePln": 859000,
      "pricePerM2": 4338,
      "areaM2": 198,
      "rooms": 5,
      "floor": null,
      "agentName": "Danuta Majchrzak",
      "listedAt": "2026-05-21",
      "lastModifiedAt": "2026-05-29",
      "firstSeenAt": "2026-05-28"
    },
    {
      "signature": "243/6093/OGS",
      "title": "Przyjemna działka ROD z domkiem ul. Gnieźnieńska",
      "category": "DZIAŁKA",
      "transaction": "SPRZEDAŻ",
      "status": "AKTUALNA",
      "city": "WĄGROWIEC",
      "district": "Gnieźnieńska",
      "locationLabel": "Gnieźnieńska, WĄGROWIEC",
      "pricePln": 67000,
      "pricePerM2": 225,
      "areaM2": 298,
      "rooms": null,
      "floor": null,
      "agentName": "Danuta Majchrzak",
      "listedAt": "2026-05-27",
      "lastModifiedAt": "2026-05-28",
      "firstSeenAt": "2026-05-28"
    },
    {
      "signature": "422/6093/OMS",
      "title": "2 pokoje w bloku z windą Wągrowiec",
      "category": "MIESZKANIE",
      "transaction": "SPRZEDAŻ",
      "status": "AKTUALNA",
      "city": "WĄGROWIEC",
      "district": "ks. Władysława Wróblewskiego",
      "locationLabel": "ks. Władysława Wróblewskiego, WĄGROWIEC",
      "pricePln": 390000,
      "pricePerM2": 7932,
      "areaM2": 49.17,
      "rooms": 2,
      "floor": 3,
      "agentName": "Danuta Majchrzak",
      "listedAt": "2026-05-27",
      "lastModifiedAt": "2026-05-29",
      "firstSeenAt": "2026-05-28"
    },
    {
      "signature": "424/6093/OMS",
      "title": "MIESZKANIE · WĄGROWIEC",
      "category": "MIESZKANIE",
      "transaction": "SPRZEDAŻ",
      "status": "AKTUALNA",
      "city": "WĄGROWIEC",
      "district": "Średnia",
      "locationLabel": "Średnia, WĄGROWIEC",
      "pricePln": 255000,
      "pricePerM2": 6764,
      "areaM2": 37.7,
      "rooms": 2,
      "floor": 3,
      "agentName": "Danuta Majchrzak",
      "listedAt": "2026-05-29",
      "lastModifiedAt": "2026-06-08",
      "firstSeenAt": "2026-06-02"
    },
    {
      "signature": "313/6093/ODS",
      "title": "Dom w Rogoźnie",
      "category": "DOM",
      "transaction": "SPRZEDAŻ",
      "status": "AKTUALNA",
      "city": "ROGOŹNO",
      "district": "Kochanowskiego",
      "locationLabel": "Kochanowskiego, ROGOŹNO",
      "pricePln": 480000,
      "pricePerM2": 2824,
      "areaM2": 170,
      "rooms": 6,
      "floor": null,
      "agentName": "Danuta Majchrzak",
      "listedAt": "2026-05-26",
      "lastModifiedAt": "2026-06-03",
      "firstSeenAt": "2026-06-03"
    },
    {
      "signature": "110/6093/OMW",
      "title": "Nowe mieszkanie 2 pokojowe Piaskowa",
      "category": "MIESZKANIE",
      "transaction": "WYNAJEM",
      "status": "AKTUALNA",
      "city": "WĄGROWIEC",
      "district": "Piaskowa",
      "locationLabel": "Piaskowa, WĄGROWIEC",
      "pricePln": 2000,
      "pricePerM2": 53,
      "areaM2": 37.76,
      "rooms": 2,
      "floor": 0,
      "agentName": "Danuta Majchrzak",
      "listedAt": "2026-05-29",
      "lastModifiedAt": "2026-06-03",
      "firstSeenAt": "2026-06-03"
    },
    {
      "signature": "244/6093/OGS",
      "title": "Działka budowlana – Prosna, gmina Budzyń,",
      "category": "DZIAŁKA",
      "transaction": "SPRZEDAŻ",
      "status": "AKTUALNA",
      "city": "PROSNA",
      "district": "",
      "locationLabel": "PROSNA",
      "pricePln": 125000,
      "pricePerM2": 99,
      "areaM2": 1260,
      "rooms": null,
      "floor": null,
      "agentName": "Danuta Majchrzak",
      "listedAt": "2026-06-03",
      "lastModifiedAt": "2026-06-08",
      "firstSeenAt": "2026-06-03"
    },
    {
      "signature": "245/6093/OGS",
      "title": "Działka z możliwością zabudowy oraz podziału",
      "category": "DZIAŁKA",
      "transaction": "SPRZEDAŻ",
      "status": "AKTUALNA",
      "city": "ZBIETKA",
      "district": "",
      "locationLabel": "ZBIETKA",
      "pricePln": 311680,
      "pricePerM2": 80,
      "areaM2": 3896,
      "rooms": null,
      "floor": null,
      "agentName": "Danuta Majchrzak",
      "listedAt": "2026-06-09",
      "lastModifiedAt": "2026-06-09",
      "firstSeenAt": "2026-06-09"
    },
    {
      "signature": "315/6093/ODS",
      "title": "Przestronny dom w świetnej lokalizacji",
      "category": "DOM",
      "transaction": "SPRZEDAŻ",
      "status": "AKTUALNA",
      "city": "ROGOŹNO",
      "district": "Kwiatowa",
      "locationLabel": "Kwiatowa, ROGOŹNO",
      "pricePln": 780000,
      "pricePerM2": 3545,
      "areaM2": 220,
      "rooms": 5,
      "floor": null,
      "agentName": "Danuta Majchrzak",
      "listedAt": "2026-06-02",
      "lastModifiedAt": "2026-06-10",
      "firstSeenAt": "2026-06-10"
    },
    {
      "signature": "425/6093/OMS",
      "title": "Mieszkanie w bloku 3-pokojowe",
      "category": "MIESZKANIE",
      "transaction": "SPRZEDAŻ",
      "status": "AKTUALNA",
      "city": "WEŁNA",
      "district": "",
      "locationLabel": "WEŁNA",
      "pricePln": 260000,
      "pricePerM2": 4489,
      "areaM2": 57.92,
      "rooms": 3,
      "floor": 1,
      "agentName": "Danuta Majchrzak",
      "listedAt": "2026-06-09",
      "lastModifiedAt": "2026-06-11",
      "firstSeenAt": "2026-06-11"
    }
  ]
}
